[
  {
    "keyword": "주식투자 모임 S&P500",
    "title": "가치투자연구소",
    "url": "https://cafe.naver.com/vilab",
    "snippet": "",
    "date": "2020.02.28.",
    "published_at": "2020-02-28T00:00:00",
    "source": "cafe",
    "crawled_at": "2025-11-22T00:17:14.631577",
    "outlet": "가치투자연구소",
    "cafe_name": "가치투자연구소",
    "thumbnail": "https://search.pstatic.net/common/?src=http%3A%2F%2Fcafefiles.naver.net%2F20160825_69%2Fgiki0125_1472094848978GtFr2_JPEG%2F%EB%A1%9C%EA%B3%A0.JPG&type=f54_54"
  },
  {
    "keyword": "주식투자 모임 S&P500",
    "title": "부산 직장인 주식 투자 스터디 E2(Entry & Exit) KOSPI,S&P500,NASDAQ 인버스 투자 결과",
    "url": "https://cafe.naver.com/vilab/148973?art=ZXh0ZXJuYWwtc2VydmljZS1uYXZlci1zZWFyY2gtY2FmZS1wcg.eyJhbGciOiJIUzI1NiIsInR5cCI6IkpXVCJ9.eyJjYWZlVHlwZSI6IkNBRkVfVVJMIiwiY2FmZVVybCI6InZpbGFiIiwiYXJ0aWNsZUlkIjoxNDg5NzMsImlzc3VlZEF0IjoxNzYzNzcwNjI3MDY2fQ.GuXeO54R7kowgshrqc_Rwvu7soZ07hF6pM9c5rgggok",
    "snippet": "",
    "date": "2020.02.28.",
    "published_at": "2020-02-28T00:00:00",
    "source": "cafe",
    "crawled_at": "2025-11-22T00:17:14.631593",
    "outlet": "가치투자연구소",
    "cafe_name": "가치투자연구소",
    "thumbnail": "https://search.pstatic.net/common/?src=http%3A%2F%2Fcafefiles.naver.net%2F20160825_69%2Fgiki0125_1472094848978GtFr2_JPEG%2F%EB%A1%9C%EA%B3%A0.JPG&type=f54_54"
  },
  {
    "keyword": "주식투자 모임 S&P500",
    "title": "[주스모] 주식 스스로 매매 모임 - 주식 공부 스터디",
    "url": "https://cafe.naver.com/stockstudy114",
    "snippet": "",
    "date": "1주 전",
    "published_at": "2025-11-15T00:17:14.631600",
    "source": "cafe",
    "crawled_at": "2025-11-22T00:17:14.631619",
    "outlet": "[주스모] 주식 스스로 매매 모임 - 주식 공부 스터디",
    "cafe_name": "[주스모] 주식 스스로 매매 모임 - 주식 공부 스터디",
    "thumbnail": "https://search.pstatic.net/common/?src=http%3A%2F%2Fcafefiles.naver.net%2FMjAyNDA4MjBfMjgg%2FMDAxNzI0MTEwNDkyMjcz.0neH2TduRJoE4MSmSQSAKdhD180CLlLwVxGkAUlO7UIg._9UIFYVUy_RSIsBjZ7AJWyMVFgyYqe9MOLURdOd87Qwg.JPEG%2F%25EC%25A3%25BC%25EC%258A%25A4%25EB%25AA%25A8_%25EB%25A1%259C%25EA%25B3%25A0.jpg&type=f54_54"
  },
  {
    "keyword": "주식투자 모임 S&P500",
    "title": "[ 11월 13일 주스모 장전 브리핑 ] 시장의 흐름이 살짝 바뀌었습니다~ !!!",
    "url": "https://cafe.naver.com/stockstudy114/119284?art=ZXh0ZXJuYWwtc2VydmljZS1uYXZlci1zZWFyY2gtY2FmZS1wcg.eyJhbGciOiJIUzI1NiIsInR5cCI6IkpXVCJ9.eyJjYWZlVHlwZSI6IkNBRkVfVVJMIiwiY2FmZVVybCI6InN0b2Nrc3R1ZHkxMTQiLCJhcnRpY2xlSWQiOjExOTI4NCwiaXNzdWVkQXQiOjE3NjM3NzA2MjcwNjZ9.tvMjfDARVumJnPDp5qMI32NtRxZKPjTYawM5SuEaS7w",
    "snippet": "",
    "date": "1주 전",
    "published_at": "2025-11-15T00:17:14.631634",
    "source": "cafe",
    "crawled_at": "2025-11-22T00:17:14.631642",
    "outlet": "[주스모] 주식 스스로 매매 모임 - 주식 공부 스터디",
    "cafe_name": "[주스모] 주식 스스로 매매 모임 - 주식 공부 스터디",
    "thumbnail": "https://search.pstatic.net/common/?src=http%3A%2F%2Fcafefiles.naver.net%2FMjAyNDA4MjBfMjgg%2FMDAxNzI0MTEwNDkyMjcz.0neH2TduRJoE4MSmSQSAKdhD180CLlLwVxGkAUlO7UIg._9UIFYVUy_RSIsBjZ7AJWyMVFgyYqe9MOLURdOd87Qwg.JPEG%2F%25EC%25A3%25BC%25EC%258A%25A4%25EB%25AA%25A8_%25EB%25A1%259C%25EA%25B3%25A0.jpg&type=f54_54"
  },
  {
    "keyword": "주식투자 모임 S&P500",
    "title": "은퇴 후 50년 [시니어·실버·노후·귀농·모임]",
    "url": "https://cafe.naver.com/dlxogns01",
    "snippet": "",
    "date": "2025.09.03.",
    "published_at": "2025-09-03T00:00:00",
    "source": "cafe",
    "crawled_at": "2025-11-22T00:17:14.631642",
    "outlet": "은퇴 후 50년 [시니어·실버·노후·귀농·모임]",
    "cafe_name": "은퇴 후 50년 [시니어·실버·노후·귀농·모임]",
    "thumbnail": "https://search.pstatic.net/common/?src=http%3A%2F%2Fcafefiles.naver.net%2FMjAyNDA4MjBfNDkg%2FMDAxNzI0MTQ1OTI5NDMx.DeQ-Yk46ww5v4jRvQxSb-tEfX7qzma8HiYaHJh7BVKUg.N6nSVP1al10PS3M1ZW-4j_ItvCzZmNFwq3M__BlWWW8g.PNG%2F%25EC%25A0%259C%25EB%25AA%25A9_%25EC%2597%2586%25EC%259D%258C4.png&type=f54_54"
  },
  {
    "keyword": "주식투자 모임 S&P500",
    "title": "나이가 들수록 고정관념도 더 커지는 것 같습니다.",
    "url": "https://cafe.naver.com/dlxogns01/306597?art=ZXh0ZXJuYWwtc2VydmljZS1uYXZlci1zZWFyY2gtY2FmZS1wcg.eyJhbGciOiJIUzI1NiIsInR5cCI6IkpXVCJ9.eyJjYWZlVHlwZSI6IkNBRkVfVVJMIiwiY2FmZVVybCI6ImRseG9nbnMwMSIsImFydGljbGVJZCI6MzA2NTk3LCJpc3N1ZWRBdCI6MTc2Mzc3MDYyNzA2Nn0.9P82FQ7aaU5Vh71a8jP1sbwIlz_NV143HlNqMbBOZv0",
    "snippet": "",
    "date": "2025.09.03.",
    "published_at": "2025-09-03T00:00:00",
    "source": "cafe",
    "crawled_at": "2025-11-22T00:17:14.631649",
    "outlet": "은퇴 후 50년 [시니어·실버·노후·귀농·모임]",
    "cafe_name": "은퇴 후 50년 [시니어·실버·노후·귀농·모임]",
    "thumbnail": "https://search.pstatic.net/common/?src=http%3A%2F%2Fcafefiles.naver.net%2FMjAyNDA4MjBfNDkg%2FMDAxNzI0MTQ1OTI5NDMx.DeQ-Yk46ww5v4jRvQxSb-tEfX7qzma8HiYaHJh7BVKUg.N6nSVP1al10PS3M1ZW-4j_ItvCzZmNFwq3M__BlWWW8g.PNG%2F%25EC%25A0%259C%25EB%25AA%25A9_%25EC%2597%2586%25EC%259D%258C4.png&type=f54_54"
  }
]