[
  {
    "keyword": "주식투자 모임 나스닥100",
    "title": "가재맨 공식 팬카페",
    "url": "https://cafe.naver.com/gajaeman",
    "snippet": "",
    "date": "1주 전",
    "published_at": "2025-11-15T00:17:36.056452",
    "source": "cafe",
    "crawled_at": "2025-11-22T00:17:36.056484",
    "outlet": "가재맨 공식 팬카페",
    "cafe_name": "가재맨 공식 팬카페",
    "thumbnail": "https://search.pstatic.net/common/?src=http%3A%2F%2Fcafefiles.naver.net%2FMjAyNTExMDlfMTk2%2FMDAxNzYyNjkwNzE4NjM4.YOE-h8vaExaops0mfyaexxgjDRaaT4-ijLxgc-TT0f0g.yOsUbN4Kh7UyrYrA8JP5_Oq0b1hrJrLJGRYTzRo5vdwg.JPEG%2FexternalFile.jpg&type=f54_54"
  },
  {
    "keyword": "주식투자 모임 나스닥100",
    "title": "아버지랑 어제 한바탕함",
    "url": "https://cafe.naver.com/gajaeman/110149?art=ZXh0ZXJuYWwtc2VydmljZS1uYXZlci1zZWFyY2gtY2FmZS1wcg.eyJhbGciOiJIUzI1NiIsInR5cCI6IkpXVCJ9.eyJjYWZlVHlwZSI6IkNBRkVfVVJMIiwiY2FmZVVybCI6ImdhamFlbWFuIiwiYXJ0aWNsZUlkIjoxMTAxNDksImlzc3VlZEF0IjoxNzYzNzcwNjQ4NjExfQ.sRQVNhGwSJAuTcDXJEaEF5YaeU6qLlyASI5HWQWtgTU",
    "snippet": "",
    "date": "1주 전",
    "published_at": "2025-11-15T00:17:36.056492",
    "source": "cafe",
    "crawled_at": "2025-11-22T00:17:36.056500",
    "outlet": "가재맨 공식 팬카페",
    "cafe_name": "가재맨 공식 팬카페",
    "thumbnail": "https://search.pstatic.net/common/?src=http%3A%2F%2Fcafefiles.naver.net%2FMjAyNTExMDlfMTk2%2FMDAxNzYyNjkwNzE4NjM4.YOE-h8vaExaops0mfyaexxgjDRaaT4-ijLxgc-TT0f0g.yOsUbN4Kh7UyrYrA8JP5_Oq0b1hrJrLJGRYTzRo5vdwg.JPEG%2FexternalFile.jpg&type=f54_54"
  },
  {
    "keyword": "주식투자 모임 나스닥100",
    "title": "미국주식 퀀트투자",
    "url": "https://cafe.naver.com/songspread",
    "snippet": "",
    "date": "4주 전",
    "published_at": "2025-10-25T00:17:36.056506",
    "source": "cafe",
    "crawled_at": "2025-11-22T00:17:36.056512",
    "outlet": "미국주식 퀀트투자",
    "cafe_name": "미국주식 퀀트투자",
    "thumbnail": "https://search.pstatic.net/common/?src=http%3A%2F%2Fcafefiles.naver.net%2FMjAyNTExMDNfMjcx%2FMDAxNzYyMTU2MDA1MjQx.DGSFlg6n1-Stk9qT6muieEHn8goM0Qni4rJcgOpAraQg.e2ZeRE4yqlvqbw7f5IyMIDsUocsneh6bqTDt-R1S0nEg.PNG%2FBus.png&type=f54_54"
  },
  {
    "keyword": "주식투자 모임 나스닥100",
    "title": "25.10.23 퀀트투자카페 10여분 회원님들과 번개 미팅 후기",
    "url": "https://cafe.naver.com/songspread/7512?art=ZXh0ZXJuYWwtc2VydmljZS1uYXZlci1zZWFyY2gtY2FmZS1wcg.eyJhbGciOiJIUzI1NiIsInR5cCI6IkpXVCJ9.eyJjYWZlVHlwZSI6IkNBRkVfVVJMIiwiY2FmZVVybCI6InNvbmdzcHJlYWQiLCJhcnRpY2xlSWQiOjc1MTIsImlzc3VlZEF0IjoxNzYzNzcwNjQ4NjExfQ.PwGdRAN6JE9ZjzKnH3OUM3nuZ_EGxgRhsgUAjx83WHY",
    "snippet": "",
    "date": "4주 전",
    "published_at": "2025-10-25T00:17:36.056518",
    "source": "cafe",
    "crawled_at": "2025-11-22T00:17:36.056524",
    "outlet": "미국주식 퀀트투자",
    "cafe_name": "미국주식 퀀트투자",
    "thumbnail": "https://search.pstatic.net/common/?src=http%3A%2F%2Fcafefiles.naver.net%2FMjAyNTExMDNfMjcx%2FMDAxNzYyMTU2MDA1MjQx.DGSFlg6n1-Stk9qT6muieEHn8goM0Qni4rJcgOpAraQg.e2ZeRE4yqlvqbw7f5IyMIDsUocsneh6bqTDt-R1S0nEg.PNG%2FBus.png&type=f54_54"
  },
  {
    "keyword": "주식투자 모임 나스닥100",
    "title": "은퇴 후 50년 [시니어·실버·노후·귀농·모임]",
    "url": "https://cafe.naver.com/dlxogns01",
    "snippet": "",
    "date": "2025.09.03.",
    "published_at": "2025-09-03T00:00:00",
    "source": "cafe",
    "crawled_at": "2025-11-22T00:17:36.056538",
    "outlet": "은퇴 후 50년 [시니어·실버·노후·귀농·모임]",
    "cafe_name": "은퇴 후 50년 [시니어·실버·노후·귀농·모임]",
    "thumbnail": "https://search.pstatic.net/common/?src=http%3A%2F%2Fcafefiles.naver.net%2FMjAyNDA4MjBfNDkg%2FMDAxNzI0MTQ1OTI5NDMx.DeQ-Yk46ww5v4jRvQxSb-tEfX7qzma8HiYaHJh7BVKUg.N6nSVP1al10PS3M1ZW-4j_ItvCzZmNFwq3M__BlWWW8g.PNG%2F%25EC%25A0%259C%25EB%25AA%25A9_%25EC%2597%2586%25EC%259D%258C4.png&type=f54_54"
  },
  {
    "keyword": "주식투자 모임 나스닥100",
    "title": "나이가 들수록 고정관념도 더 커지는 것 같습니다.",
    "url": "https://cafe.naver.com/dlxogns01/306597?art=ZXh0ZXJuYWwtc2VydmljZS1uYXZlci1zZWFyY2gtY2FmZS1wcg.eyJhbGciOiJIUzI1NiIsInR5cCI6IkpXVCJ9.eyJjYWZlVHlwZSI6IkNBRkVfVVJMIiwiY2FmZVVybCI6ImRseG9nbnMwMSIsImFydGljbGVJZCI6MzA2NTk3LCJpc3N1ZWRBdCI6MTc2Mzc3MDY0ODYxMX0.0B_MpLlZQHgUnQzrYBhqohPwecognNJGl0QF-HwFNyY",
    "snippet": "",
    "date": "2025.09.03.",
    "published_at": "2025-09-03T00:00:00",
    "source": "cafe",
    "crawled_at": "2025-11-22T00:17:36.056546",
    "outlet": "은퇴 후 50년 [시니어·실버·노후·귀농·모임]",
    "cafe_name": "은퇴 후 50년 [시니어·실버·노후·귀농·모임]",
    "thumbnail": "https://search.pstatic.net/common/?src=http%3A%2F%2Fcafefiles.naver.net%2FMjAyNDA4MjBfNDkg%2FMDAxNzI0MTQ1OTI5NDMx.DeQ-Yk46ww5v4jRvQxSb-tEfX7qzma8HiYaHJh7BVKUg.N6nSVP1al10PS3M1ZW-4j_ItvCzZmNFwq3M__BlWWW8g.PNG%2F%25EC%25A0%259C%25EB%25AA%25A9_%25EC%2597%2586%25EC%259D%258C4.png&type=f54_54"
  }
]